wrapc.py
wrapc-0.0.3.dist-info/entry_points.txt
wrapc-0.0.3.dist-info/WHEEL
wrapc-0.0.3.dist-info/METADATA
wrapc-0.0.3.dist-info/RECORD
